setup.cfg
setup.py
ssh_keydb/__init__.py
ssh_keydb/akcmp.py
ssh_keydb/ssh_keydb.py
ssh_keydb.egg-info/PKG-INFO
ssh_keydb.egg-info/SOURCES.txt
ssh_keydb.egg-info/dependency_links.txt
ssh_keydb.egg-info/entry_points.txt
ssh_keydb.egg-info/requires.txt
ssh_keydb.egg-info/top_level.txt
ssh_keydb/plugins/__init__.py
ssh_keydb/plugins/generator.py
ssh_keydb/plugins/group.py
ssh_keydb/plugins/help.py
ssh_keydb/plugins/key.py
ssh_keydb/plugins/location.py
ssh_keydb/plugins/membership.py
ssh_keydb/plugins/model.py
ssh_keydb/plugins/permission.py
ssh_keydb/plugins/profile.py
ssh_keydb/plugins/role.py
ssh_keydb/plugins/server.py
ssh_keydb/plugins/user.py