Metadata-Version: 1.0
Name: ssh-keydb
Version: 0.2dev
Summary: OpenSSH public key management tool
Home-page: http://code.google.com/p/ssh-keydb/
Author: Fabien Bouleau
Author-email: fabien.bouleau@gmail.com
License: GPLv3
Keywords: openssh public key management tool
Platform: UNKNOWN
